plone.autoinclude-2.0.5-py3.13-nspkg.pth
plone/autoinclude/__init__.py
plone/autoinclude/loader.py
plone/autoinclude/meta.zcml
plone/autoinclude/zcml.py
plone/autoinclude/ploneinclude/__init__.py
plone/autoinclude/ploneinclude/configure.zcml
plone/autoinclude/ploneinclude/meta.zcml
plone/autoinclude/ploneinclude/overrides.zcml
plone/autoinclude/tests/__init__.py
plone/autoinclude/tests/test_loader.py
plone/autoinclude/tests/utils.py
plone_autoinclude-2.0.5.dist-info/licenses/LICENSE.GPL
plone_autoinclude-2.0.5.dist-info/licenses/LICENSE.rst
plone_autoinclude-2.0.5.dist-info/METADATA
plone_autoinclude-2.0.5.dist-info/WHEEL
plone_autoinclude-2.0.5.dist-info/namespace_packages.txt
plone_autoinclude-2.0.5.dist-info/top_level.txt
plone_autoinclude-2.0.5.dist-info/RECORD
