Metadata-Version: 2.4
Name: plone.autoinclude
Version: 2.0.5
Summary: Auto include code and zcml
Home-page: https://github.com/collective/plone.autoinclude
Author: Maurits van Rees
Author-email: maurits@vanrees.org
License: GPL version 2
Project-URL: PyPI, https://pypi.org/project/plone.autoinclude/
Project-URL: Source, https://github.com/plone/plone.autoinclude
Project-URL: Tracker, https://github.com/plone/plone.autoinclude/issues
Keywords: Python Plone CMS
Classifier: Development Status :: 5 - Production/Stable
Classifier: Environment :: Web Environment
Classifier: Framework :: Plone :: 6.0
Classifier: Framework :: Plone :: 6.1
Classifier: Framework :: Plone :: 6.2
Classifier: Framework :: Plone :: Core
Classifier: Framework :: Plone
Classifier: License :: OSI Approved :: GNU General Public License v2 (GPLv2)
Classifier: Operating System :: OS Independent
Classifier: Programming Language :: Python :: 3.9
Classifier: Programming Language :: Python :: 3.10
Classifier: Programming Language :: Python :: 3.11
Classifier: Programming Language :: Python :: 3.12
Classifier: Programming Language :: Python :: 3.13
Classifier: Programming Language :: Python :: Implementation :: CPython
Classifier: Programming Language :: Python
Requires-Python: >=3.9
License-File: LICENSE.GPL
License-File: LICENSE.rst
Requires-Dist: importlib-metadata; python_version < "3.10"
Requires-Dist: setuptools
Requires-Dist: zope.configuration
Dynamic: author
Dynamic: author-email
Dynamic: classifier
Dynamic: home-page
Dynamic: keywords
Dynamic: license
Dynamic: license-file
Dynamic: project-url
Dynamic: requires-dist
Dynamic: requires-python
Dynamic: summary
